__init__.py
breadboard_python/__init__.py
breadboard_python/accumulating_context.py
breadboard_python/chat_gpt_3_5_turbo.py
breadboard_python/coffeebot.py
breadboard_python/echo.py
breadboard_python/import_node.py
breadboard_python/main.py
breadboard_python/math.py
breadboard_python/trivial-tool.py
breadboard_python-0.1.0.dist-info/LICENSE
breadboard_python-0.1.0.dist-info/METADATA
breadboard_python-0.1.0.dist-info/WHEEL
breadboard_python-0.1.0.dist-info/top_level.txt
breadboard_python-0.1.0.dist-info/RECORD
