Metadata-Version: 2.1
Name: breadboard_python
Version: 0.1.0
Summary: A Python library for defining Breadboards.
Author-email: Kevin Xiao <xiaok10003@gmail.com>
License: 
Keywords: breadboard
Requires-Python: >=3.8
License-File: LICENSE
Requires-Dist: pydantic
Requires-Dist: javascript
Requires-Dist: jsonref
Requires-Dist: json-fix
Requires-Dist: prettydiff
